temper_dir/__main__.py
temper_dir/dir_creator.py
temper_dir/tests/test_basic.py
temper_dir-0.0.9.dist-info/LICENSE
temper_dir-0.0.9.dist-info/METADATA
temper_dir-0.0.9.dist-info/WHEEL
temper_dir-0.0.9.dist-info/entry_points.txt
temper_dir-0.0.9.dist-info/top_level.txt
temper_dir-0.0.9.dist-info/RECORD
