Metadata-Version: 2.1
Name: temper-dir
Version: 0.0.9
Summary: A simple CLI tool to create temporary directories
Author: Itay Shoshani
License-File: LICENSE
